[
{
  "directory": "/home/popes/Desktop/3ºAno 2ºSemestre/CGBLA3/cg24/code/build",
  "command": "/usr/bin/g++  -I\"/home/popes/Desktop/3ºAno 2ºSemestre/CGBLA3/cg24/code/Include\" -isystem /usr/include/IL -g -o CMakeFiles/engine.dir/engine.cpp.o -c \"/home/popes/Desktop/3ºAno 2ºSemestre/CGBLA3/cg24/code/engine.cpp\"",
  "file": "/home/popes/Desktop/3ºAno 2ºSemestre/CGBLA3/cg24/code/engine.cpp",
  "output": "CMakeFiles/engine.dir/engine.cpp.o"
},
{
  "directory": "/home/popes/Desktop/3ºAno 2ºSemestre/CGBLA3/cg24/code/build",
  "command": "/usr/bin/g++  -I\"/home/popes/Desktop/3ºAno 2ºSemestre/CGBLA3/cg24/code/Include\" -isystem /usr/include/IL -g -o CMakeFiles/engine.dir/tinyxml2-master/tinyxml2.cpp.o -c \"/home/popes/Desktop/3ºAno 2ºSemestre/CGBLA3/cg24/code/tinyxml2-master/tinyxml2.cpp\"",
  "file": "/home/popes/Desktop/3ºAno 2ºSemestre/CGBLA3/cg24/code/tinyxml2-master/tinyxml2.cpp",
  "output": "CMakeFiles/engine.dir/tinyxml2-master/tinyxml2.cpp.o"
},
{
  "directory": "/home/popes/Desktop/3ºAno 2ºSemestre/CGBLA3/cg24/code/build",
  "command": "/usr/bin/g++  -I\"/home/popes/Desktop/3ºAno 2ºSemestre/CGBLA3/cg24/code/Include\" -g -o CMakeFiles/generator.dir/generator.cpp.o -c \"/home/popes/Desktop/3ºAno 2ºSemestre/CGBLA3/cg24/code/generator.cpp\"",
  "file": "/home/popes/Desktop/3ºAno 2ºSemestre/CGBLA3/cg24/code/generator.cpp",
  "output": "CMakeFiles/generator.dir/generator.cpp.o"
}
]